{
	"name": "Lazarus Resurrection Theme",
	"type": "dark",
	"colors": {
		"editor.background": "#fafafa",
		"editor.foreground": "#39acb5",
		"quickInput.background": "#fafafa",
		"sideBar.background": "#fafafa",
		"editorHoverWidget.background": "#fafafa",
	},
	"tokenColors": [
		{
			"scope": [
				"comment",
				"punctuation.definition.comment"
			],
			"settings": {
				"foreground": "#546e7a",
				"fontStyle": "italic"
			}
		},
		{
			"scope": [
				"keyword",
				"storage"
			],
			"settings": {
				"foreground": "#90b758",
			}
		},
		{
			"scope": [
				"variable",
				"variable.parameter"
			],
			"settings": {
				"foreground": "#39acb5"
			}
		},
		{
			"scope": [
				"string",
				"punctuation.definition.string"
			],
			"settings": {
				"foreground": "#90b758"
			}
		},
		{
			"scope": [
				"entity.name.tag",
				"entity.name.tag.html"
			],
			"settings": {
				"foreground": "#ef7078"
			}
		},
		{
			"scope": [
				"entity.other.attribute-name"
			],
			"settings": {
				"foreground": "#9c3ed9"
			}
		},
		{
			"scope": [
				"support.class",
				"support.type"
			],
			"settings": {
				"foreground": "#e1921d"
			}
		},
		{
			"scope": [
				"meta.selector.css",
				"entity.name.tag.css"
			],
			"settings": {
				"foreground": "#5EEAD4"
			}
		},
		{
			"scope": [
				"meta.property-name.css"
			],
			"settings": {
				"foreground": "#93C5FD"
			}
		},
		{
			"scope": [
				"meta.property-value.css"
			],
			"settings": {
				"foreground": "#86EFAC"
			}
		},
		{
			"scope": [
				"invalid"
			],
			"settings": {
				"foreground": "#FB7185"
			}
		},
		{
			"scope": "entity.name.function",
			"settings": {
				"foreground": "#6082b8"
			}
		},
		{
			"scope": [
				"variable.other",
				"variable.other.local"
			],
			"settings": {
				"foreground": "#8fa4ae"
			}
		},
		{
			"scope": [
				"variable.other.global"
			],
			"settings": {
				"foreground": "#8fa4ae"
			}
		},
		{
			"scope": [
				"variable.other.readwrite",
				"variable.other.readwrite.js"
			],
			"settings": {
				"foreground": "#8fa4ae"
			}
		},
		{
			"scope": "storage.modifier.php",
			"settings": {
				"foreground": "#9c3ed9"
			}
		},
		{
			"scope": "storage.modifier.static.php",
			"settings": {
				"foreground": "#9c3ed9"
			}
		},
		{
			"scope": "storage.type.php",
			"settings": {
				"foreground": "#F78C6C"
			}
		},
		{
			"scope": "variable.other.php",
			"settings": {
				"foreground": "#8fa4ae"
			}
		},
		{
			"scope": [
				"keyword.operator.assignment.php",
				"constant.numeric.php"
			],
			"settings": {
				"foreground": "#F78C6C"
			}
		},
		{
			"scope": [
				"markup.heading.markdown",
				"markup.bold.markdown",
				"markup.italic.markdown",
				"markup.inline.raw.markdown",
				"text.markdown",
				"punctuation.definition.heading.markdown",
				"punctuation.definition.bold.markdown",
				"punctuation.definition.italic.markdown"
			],
			"settings": {
				"foreground": "#39acb5" // pure white
			}
		}
	]
}